kinetix/__init__.py
kinetix/editor.py
kinetix/assets/circle.png
kinetix/assets/edit.png
kinetix/assets/fjoint.png
kinetix/assets/fjoint2.png
kinetix/assets/hand.png
kinetix/assets/joint.png
kinetix/assets/play.png
kinetix/assets/rjoint.png
kinetix/assets/rjoint2.png
kinetix/assets/rotate.png
kinetix/assets/square.png
kinetix/assets/thruster.png
kinetix/assets/thruster6.png
kinetix/assets/triangle.png
kinetix/environment/__init__.py
kinetix/environment/env.py
kinetix/environment/env_state.py
kinetix/environment/spaces.py
kinetix/environment/utils.py
kinetix/environment/wrappers.py
kinetix/environment/ued/distributions.py
kinetix/environment/ued/mutators.py
kinetix/environment/ued/ued.py
kinetix/environment/ued/ued_state.py
kinetix/environment/ued/util.py
kinetix/levels/l/car_launch.json
kinetix/levels/l/car_swing_around.json
kinetix/levels/l/chain_lander.json
kinetix/levels/l/chain_thrust.json
kinetix/levels/l/gears.json
kinetix/levels/l/grasp_easy.json
kinetix/levels/l/grasp_hard.json
kinetix/levels/l/h0_angrybirds.json
kinetix/levels/l/h10_morph_direction_2.json
kinetix/levels/l/h11_obstacle_avoidance.json
kinetix/levels/l/h12_platformer_1.json
kinetix/levels/l/h13_platformer_2.json
kinetix/levels/l/h14_simple_thruster.json
kinetix/levels/l/h15_swing_up.json
kinetix/levels/l/h16_thruster_goal.json
kinetix/levels/l/h17_unicycle.json
kinetix/levels/l/h1_car_left.json
kinetix/levels/l/h2_car_ramp.json
kinetix/levels/l/h3_car_right.json
kinetix/levels/l/h4_cartpole.json
kinetix/levels/l/h5_flappy_bird.json
kinetix/levels/l/h6_lorry.json
kinetix/levels/l/h7_maze_1.json
kinetix/levels/l/h8_maze_2.json
kinetix/levels/l/h9_morph_direction.json
kinetix/levels/l/hard_beam_balance.json
kinetix/levels/l/hard_cartpole_thrust.json
kinetix/levels/l/hard_cartpole_wheels.json
kinetix/levels/l/hard_lunar_lander.json
kinetix/levels/l/hard_pinball.json
kinetix/levels/l/lever_puzzle.json
kinetix/levels/l/mjc_half_cheetah.json
kinetix/levels/l/mjc_half_cheetah_easy.json
kinetix_env-2.0.4.dist-info/licenses/LICENSE
kinetix_env-2.0.4.dist-info/METADATA
kinetix_env-2.0.4.dist-info/WHEEL
kinetix_env-2.0.4.dist-info/top_level.txt
kinetix_env-2.0.4.dist-info/RECORD
