Metadata-Version: 2.4
Name: kinetix-env
Version: 2.0.4
Summary: An open-ended space of 2D physics-based RL environments
Author-email: Michael Matthews <michael.matthews@eng.ox.ac.uk>, Michael Beukman <michael.beukman@eng.ox.ac.uk>
Project-URL: Homepage, https://github.com/FLAIROx/Kinetix
Project-URL: Issues, https://github.com/FLAIROx/Kinetix/Issues
Classifier: Programming Language :: Python :: 3
Classifier: License :: OSI Approved :: MIT License
Classifier: Operating System :: OS Independent
Requires-Python: >=3.10
License-File: LICENSE
Requires-Dist: jax<=0.9.0,>=0.4.37
Requires-Dist: distrax
Requires-Dist: optax
Requires-Dist: flax>=0.10.4
Requires-Dist: numpy
Requires-Dist: argparse
Requires-Dist: wandb
Requires-Dist: orbax-checkpoint
Requires-Dist: pygame
Requires-Dist: gymnax
Requires-Dist: chex
Requires-Dist: matplotlib
Requires-Dist: imageio
Requires-Dist: seaborn
Requires-Dist: hydra-core
Requires-Dist: safetensors
Requires-Dist: pygame_widgets==1.1.5
Requires-Dist: jaxgl
Requires-Dist: jax2d==1.0.1
Requires-Dist: moviepy==1.0.3
Dynamic: license-file
